mollusc/__init__.py
mollusc/dist.py
mollusc/sh.py
mollusc/util.py
mollusc/venv.py
mollusc-0.0.5.dist-info/DESCRIPTION.rst
mollusc-0.0.5.dist-info/LICENSE.txt
mollusc-0.0.5.dist-info/METADATA
mollusc-0.0.5.dist-info/RECORD
mollusc-0.0.5.dist-info/WHEEL
mollusc-0.0.5.dist-info/metadata.json
mollusc-0.0.5.dist-info/top_level.txt
