Metadata-Version: 2.0
Name: mollusc
Version: 0.0.5
Summary: Bootstrap your Python projects
Home-page: https://github.com/bachew/mollusc
Author: Chew Boon Aik
Author-email: bachew@gmail.com
License: MIT
Download-URL: https://github.com/bachew/mollusc/archive/master.zip
Platform: UNKNOWN
Classifier: Development Status :: 4 - Beta
Classifier: Environment :: Console
Classifier: License :: OSI Approved :: MIT License
Classifier: Operating System :: POSIX :: Linux
Classifier: Programming Language :: Python :: 2.7
Classifier: Programming Language :: Python :: 3
Classifier: Topic :: Software Development :: Build Tools
Classifier: Topic :: Utilities
Requires-Dist: six (>=1.11.0)
